himpunan_sigma/__init__.py
himpunan_sigma-0.2.2.dist-info/METADATA
himpunan_sigma-0.2.2.dist-info/WHEEL
himpunan_sigma-0.2.2.dist-info/top_level.txt
himpunan_sigma-0.2.2.dist-info/RECORD
