Metadata-Version: 2.1
Name: himpunan_sigma
Version: 0.2.2
Summary: Implementasi Himpunan Python untuk Tugas Matematika Diskrit
Author: Mimimi
Author-email: swissarchipelago@gmail.com
Classifier: Programming Language :: Python :: 3
Classifier: License :: OSI Approved :: MIT License
Classifier: Operating System :: OS Independent
Classifier: Topic :: Scientific/Engineering :: Mathematics
Requires-Python: >=3.6
